AUTHORS.rst
CONTRIBUTING.rst
HISTORY.rst
LICENSE
MANIFEST.in
README.rst
setup.cfg
setup.py
parrot_integrations/account_service/__init__.py
parrot_integrations/account_service/account_types/__init__.py
parrot_integrations/account_service/account_types/account_type_created.py
parrot_integrations/account_service/account_types/account_type_updated.py
parrot_integrations/account_service/account_types/create_account_type.py
parrot_integrations/account_service/account_types/get_account_type.py
parrot_integrations/account_service/account_types/search_account_types.py
parrot_integrations/account_service/account_types/update_account_type.py
parrot_integrations/account_service/accounts/__init__.py
parrot_integrations/account_service/accounts/account_created.py
parrot_integrations/account_service/accounts/account_updated.py
parrot_integrations/account_service/accounts/create_account.py
parrot_integrations/account_service/accounts/get_account.py
parrot_integrations/account_service/accounts/search_accounts.py
parrot_integrations/account_service/accounts/update_account.py
parrot_integrations/approval_service/__init__.py
parrot_integrations/approval_service/comments/__init__.py
parrot_integrations/approval_service/comments/comment_created.py
parrot_integrations/approval_service/comments/create_comment.py
parrot_integrations/approval_service/comments/get_comment.py
parrot_integrations/approval_service/comments/search_comments.py
parrot_integrations/approval_service/submission_types/__init__.py
parrot_integrations/approval_service/submission_types/create_submission_type.py
parrot_integrations/approval_service/submission_types/get_submission_type.py
parrot_integrations/approval_service/submission_types/search_submission_types.py
parrot_integrations/approval_service/submission_types/submission_type_created.py
parrot_integrations/approval_service/submission_types/submission_type_updated.py
parrot_integrations/approval_service/submission_types/update_submission_type.py
parrot_integrations_core.egg-info/PKG-INFO
parrot_integrations_core.egg-info/SOURCES.txt
parrot_integrations_core.egg-info/dependency_links.txt
parrot_integrations_core.egg-info/not-zip-safe
parrot_integrations_core.egg-info/requires.txt
parrot_integrations_core.egg-info/top_level.txt