Metadata-Version: 2.1
Name: parrot-integrations-core
Version: 0.0.18
Summary: Python Integration Project Framework
Home-page: https://github.com/perrystallings/parrot_integrations_core
Author: Perry Stallings
Author-email: astal01@gmail.com
License: MIT license
Keywords: parrot_integrations
Classifier: Development Status :: 2 - Pre-Alpha
Classifier: Intended Audience :: Developers
Classifier: License :: OSI Approved :: MIT License
Classifier: Natural Language :: English
Classifier: Programming Language :: Python :: 3
Classifier: Programming Language :: Python :: 3.6
Classifier: Programming Language :: Python :: 3.7
Classifier: Programming Language :: Python :: 3.8
Requires-Python: >=3.6
License-File: LICENSE
License-File: AUTHORS.rst
Requires-Dist: jsonpath-ng
Requires-Dist: croniter
Requires-Dist: jsonschema
